pypath/__init__.py
pypath/_metadata.py
pypath/biocypher/__init__.py
pypath/biocypher/adapter.py
pypath/core/__init__.py
pypath/core/annot.py
pypath/core/attrs.py
pypath/core/common.py
pypath/core/complex.py
pypath/core/entity.py
pypath/core/enz_sub.py
pypath/core/evidence.py
pypath/core/interaction.py
pypath/core/intercell.py
pypath/core/intercell_annot.py
pypath/core/network.py
pypath/data/__init__.py
pypath/data/_data.py
pypath/data/embl_colors
pypath/data/ensembl_biomart_query.xml
pypath/data/goose_ancestors.sql
pypath/data/goose_annotations.sql
pypath/data/goose_terms.sql
pypath/data/licenses/afl_v3.json
pypath/data/licenses/apache_2.0.json
pypath/data/licenses/artistic_2.0.json
pypath/data/licenses/biocarta.json
pypath/data/licenses/bsd.json
pypath/data/licenses/cc_by_2.5.json
pypath/data/licenses/cc_by_3.0.json
pypath/data/licenses/cc_by_4.0.json
pypath/data/licenses/cc_by_nc-nd_3.0.json
pypath/data/licenses/cc_by_nc-nd_4.0.json
pypath/data/licenses/cc_by_nc_2.0.json
pypath/data/licenses/cc_by_nc_3.0.json
pypath/data/licenses/cc_by_nc_4.0.json
pypath/data/licenses/cc_by_nc_sa_3.0.json
pypath/data/licenses/cc_by_nc_sa_4.0.json
pypath/data/licenses/cc_by_nd_3.0.json
pypath/data/licenses/cc_by_nd_4.0.json
pypath/data/licenses/cc_by_sa_2.5.json
pypath/data/licenses/cc_by_sa_3.0.json
pypath/data/licenses/cc_by_sa_4.0.json
pypath/data/licenses/cc_zero.json
pypath/data/licenses/cellcellinteractions.json
pypath/data/licenses/composite.json
pypath/data/licenses/cosmic.json
pypath/data/licenses/cytosig.json
pypath/data/licenses/dsl.json
pypath/data/licenses/elm.json
pypath/data/licenses/embl-ebi.json
pypath/data/licenses/eul.json
pypath/data/licenses/gnu_gpl_v2.json
pypath/data/licenses/gnu_gpl_v3.json
pypath/data/licenses/gnu_lgpl_v3.json
pypath/data/licenses/hgnc.json
pypath/data/licenses/hpo.json
pypath/data/licenses/hprd.json
pypath/data/licenses/i2d.json
pypath/data/licenses/informal.json
pypath/data/licenses/kegg.json
pypath/data/licenses/kinase-com.json
pypath_omnipath-0.16.20.dist-info/LICENSE
pypath_omnipath-0.16.20.dist-info/METADATA
pypath_omnipath-0.16.20.dist-info/WHEEL
pypath_omnipath-0.16.20.dist-info/entry_points.txt
pypath_omnipath-0.16.20.dist-info/RECORD
