Metadata-Version: 2.1
Name: pypath-omnipath
Version: 0.16.20
Summary: Molecular signaling prior knowledge processing
Home-page: https://omnipathdb.org/
License: GPL-3.0-only
Keywords: systems biology,molecular biology,omics,network,signaling
Author: Denes Turei
Author-email: turei.denes@gmail.com
Requires-Python: >=3.9,<4.0
Classifier: Development Status :: 4 - Beta
Classifier: Intended Audience :: Developers
Classifier: Intended Audience :: Science/Research
Classifier: License :: OSI Approved :: GNU General Public License v3 (GPLv3)
Classifier: Natural Language :: English
Classifier: Operating System :: OS Independent
Classifier: Programming Language :: Python
Classifier: Programming Language :: Python :: 3
Classifier: Programming Language :: Python :: 3.9
Classifier: Programming Language :: Python :: 3.10
Classifier: Programming Language :: Python :: 3.11
Classifier: Programming Language :: Python :: 3.12
Classifier: Programming Language :: Python :: 3.13
Classifier: Topic :: Scientific/Engineering :: Bio-Informatics
Classifier: Topic :: Scientific/Engineering :: Information Analysis
Classifier: Topic :: Scientific/Engineering :: Mathematics
Classifier: Topic :: Software Development :: Libraries :: Python Modules
Provides-Extra: graph
Provides-Extra: metabo
Provides-Extra: pathophenodb
Requires-Dist: PyYAML
Requires-Dist: beautifulsoup4
Requires-Dist: certifi (>=2023.7.22)
Requires-Dist: cffi (>=1.17.0,<2.0.0)
Requires-Dist: cryptography (>=41.0.4)
Requires-Dist: dill
Requires-Dist: epam.indigo ; extra == "metabo"
Requires-Dist: future
Requires-Dist: glom
Requires-Dist: lxml
Requires-Dist: matplotlib
Requires-Dist: numpy
Requires-Dist: openbabel ; extra == "metabo"
Requires-Dist: openpyxl
Requires-Dist: pandas
Requires-Dist: psutil
Requires-Dist: pycurl
Requires-Dist: pypath-common (>=0.2.6)
Requires-Dist: pyreadr
Requires-Dist: pysftp (>=0.2.9,<0.3.0)
Requires-Dist: python-igraph ; extra == "graph"
Requires-Dist: rdata
Requires-Dist: rdkit ; extra == "metabo"
Requires-Dist: requests
Requires-Dist: scipy (>=1.9.0)
Requires-Dist: sparqlwrapper ; extra == "pathophenodb"
Requires-Dist: sqlparse
Requires-Dist: tabulate
Requires-Dist: timeloop
Requires-Dist: toml
Requires-Dist: tornado (>=3.6.6)
Requires-Dist: tqdm
Requires-Dist: typing_extensions
Requires-Dist: xlrd
Project-URL: Bug Tracker, https://github.com/saezlab/pypath/issues
Project-URL: Repository, https://github.com/saezlab/pypath
